post_service/__init__.py
post_service/main.py
devops_post_service_project_2022-1.4.1.dist-info/METADATA
devops_post_service_project_2022-1.4.1.dist-info/WHEEL
devops_post_service_project_2022-1.4.1.dist-info/top_level.txt
devops_post_service_project_2022-1.4.1.dist-info/RECORD
