Metadata-Version: 2.1
Name: devops-post-service-project-2022
Version: 1.4.1
Summary: UNKNOWN
Home-page: UNKNOWN
License: UNKNOWN
Platform: UNKNOWN
Requires-Dist: fastapi
Requires-Dist: fastapi-contrib
Requires-Dist: uvicorn
Requires-Dist: pydantic
Requires-Dist: typing
Requires-Dist: kafka-python
Requires-Dist: pymongo
Requires-Dist: mongomock
Requires-Dist: PyJWT
Requires-Dist: jaeger-client
Requires-Dist: opentracing
Requires-Dist: prometheus-fastapi-instrumentator
Requires-Dist: python-multipart
